ses_send/__init__.py
ses_send/send.py
ses_send-1.0.3.dist-info/LICENSE
ses_send-1.0.3.dist-info/METADATA
ses_send-1.0.3.dist-info/WHEEL
ses_send-1.0.3.dist-info/top_level.txt
ses_send-1.0.3.dist-info/RECORD
