Metadata-Version: 2.1
Name: ses-send
Version: 1.0.3
Summary: Simple wrapper to send emails via AWS SES
Home-page: https://github.com/replicant0wnz/ses-send
Author: Glenn E. Bailey III
Author-email: glenn@dronemusic.co
License: UNKNOWN
Project-URL: Bug Tracker, https://github.com/replicant0wnz/ses-send/issues
Platform: UNKNOWN
Classifier: Programming Language :: Python :: 3
Classifier: Operating System :: OS Independent
Requires-Python: >=3.6
License-File: LICENSE
Requires-Dist: boto3
Requires-Dist: pyyaml
